{
  "manifestVersion": "3.2",
  "proxies": [
    {
      "address": "0x51292952F3D33d082E433d9E2c92Ea482dfC336A",
      "txHash": "0x64aea2a6ca21bb9724c4cbd11ad278c2280ae65e39a077a7ebe599e11ddf9d8e",
      "kind": "transparent"
    },
    {
      "address": "0x6b92A17CFdC60df4c1A22Df3D76E9a2a69a9AD1B",
      "txHash": "0x19d88b1f61d98cbf4635e05135907c899f0525ee0d25bd314b4096ea5a0f4d95",
      "kind": "transparent"
    },
    {
      "address": "0x76c92A8a72cB1D15a2fd9742f84ef4bC71466880",
      "txHash": "0x45726094b40712559bda1e0378730800c59164dd3bcc76dee44025e76f46619a",
      "kind": "transparent"
    },
    {
      "address": "0x14c7627738464A70A127A988db65C94B909f1482",
      "txHash": "0xc13e675e29b68418bd774b6b6893e8ddc608d289369acb73a2567aa72832cc2d",
      "kind": "transparent"
    },
    {
      "address": "0xE0103FACaFb4440D3C8CE41A1602796C57171EdA",
      "txHash": "0x5d1eaf2aa26646a1ab2f868ef97ef572efb2beab057f7a6ad5c77ff6d5e59e9d",
      "kind": "transparent"
    },
    {
      "address": "0xA55353d56514292275D460c8a455410b67FCc8eA",
      "txHash": "0x2061f7ed6625cc1b89fd9d1727ed2a496b7b2be8f3dcb34d1d79ea705c3dbd7d",
      "kind": "transparent"
    }
  ],
  "impls": {
    "4e6a8fc488e060c6a6d0b01ab4df148ecb04072b2fea51af0f97508ccdfc6da0": {
      "address": "0x08C39316C7B691EBF7EcFb9F068A6155947A498b",
      "txHash": "0xb421b5ae3f2b3bd047c775c71e0eba80905b9ce19b2a101fea8946e8db27340d",
      "layout": {
        "solcVersion": "0.8.20",
        "storage": [
          {
            "label": "groups",
            "offset": 0,
            "slot": "0",
            "type": "t_mapping(t_uint256,t_struct(Group)4871_storage)",
            "contract": "GroupMembership",
            "src": "contracts/Dev/GroupMembership.sol:64"
          },
          {
            "label": "dappSettingSnapshot",
            "offset": 0,
            "slot": "1",
            "type": "t_mapping(t_uint256,t_struct(DappSettingSnapshot)4849_storage)",
            "contract": "GroupMembership",
            "src": "contracts/Dev/GroupMembership.sol:65"
          },
          {
            "label": "originalGroupBondValues",
            "offset": 0,
            "slot": "2",
            "type": "t_mapping(t_uint256,t_uint256)",
            "contract": "GroupMembership",
            "src": "contracts/Dev/GroupMembership.sol:66"
          },
          {
            "label": "originalSumGroupBondValues",
            "offset": 0,
            "slot": "3",
            "type": "t_mapping(t_uint256,t_uint256)",
            "contract": "GroupMembership",
            "src": "contracts/Dev/GroupMembership.sol:67"
          },
          {
            "label": "joinTimestamps",
            "offset": 0,
            "slot": "4",
            "type": "t_mapping(t_uint256,t_uint256)",
            "contract": "GroupMembership",
            "src": "contracts/Dev/GroupMembership.sol:68"
          },
          {
            "label": "groupTimeBonusesKeys",
            "offset": 0,
            "slot": "5",
            "type": "t_mapping(t_uint256,t_array(t_uint256)dyn_storage)",
            "contract": "GroupMembership",
            "src": "contracts/Dev/GroupMembership.sol:70"
          },
          {
            "label": "groupTimeBonuses",
            "offset": 0,
            "slot": "6",
            "type": "t_mapping(t_uint256,t_mapping(t_uint256,t_uint256))",
            "contract": "GroupMembership",
            "src": "contracts/Dev/GroupMembership.sol:71"
          },
          {
            "label": "dappAddress",
            "offset": 0,
            "slot": "7",
            "type": "t_address",
            "contract": "GroupMembership",
            "src": "contracts/Dev/GroupMembership.sol:73"
          }
        ],
        "types": {
          "t_address": {
            "label": "address",
            "numberOfBytes": "20"
          },
          "t_bool": {
            "label": "bool",
            "numberOfBytes": "1"
          },
          "t_mapping(t_address,t_bool)": {
            "label": "mapping(address => bool)",
            "numberOfBytes": "32"
          },
          "t_mapping(t_address,t_mapping(t_address,t_bool))": {
            "label": "mapping(address => mapping(address => bool))",
            "numberOfBytes": "32"
          },
          "t_mapping(t_address,t_uint256)": {
            "label": "mapping(address => uint256)",
            "numberOfBytes": "32"
          },
          "t_mapping(t_uint256,t_address)": {
            "label": "mapping(uint256 => address)",
            "numberOfBytes": "32"
          },
          "t_string_storage": {
            "label": "string",
            "numberOfBytes": "32"
          },
          "t_struct(ERC721Storage)267_storage": {
            "label": "struct ERC721Upgradeable.ERC721Storage",
            "members": [
              {
                "label": "_name",
                "type": "t_string_storage",
                "offset": 0,
                "slot": "0"
              },
              {
                "label": "_symbol",
                "type": "t_string_storage",
                "offset": 0,
                "slot": "1"
              },
              {
                "label": "_owners",
                "type": "t_mapping(t_uint256,t_address)",
                "offset": 0,
                "slot": "2"
              },
              {
                "label": "_balances",
                "type": "t_mapping(t_address,t_uint256)",
                "offset": 0,
                "slot": "3"
              },
              {
                "label": "_tokenApprovals",
                "type": "t_mapping(t_uint256,t_address)",
                "offset": 0,
                "slot": "4"
              },
              {
                "label": "_operatorApprovals",
                "type": "t_mapping(t_address,t_mapping(t_address,t_bool))",
                "offset": 0,
                "slot": "5"
              }
            ],
            "numberOfBytes": "192"
          },
          "t_struct(InitializableStorage)65_storage": {
            "label": "struct Initializable.InitializableStorage",
            "members": [
              {
                "label": "_initialized",
                "type": "t_uint64",
                "offset": 0,
                "slot": "0"
              },
              {
                "label": "_initializing",
                "type": "t_bool",
                "offset": 8,
                "slot": "0"
              }
            ],
            "numberOfBytes": "32"
          },
          "t_uint256": {
            "label": "uint256",
            "numberOfBytes": "32"
          },
          "t_uint64": {
            "label": "uint64",
            "numberOfBytes": "8"
          },
          "t_array(t_uint256)dyn_storage": {
            "label": "uint256[]",
            "numberOfBytes": "32"
          },
          "t_enum(GroupType)4839": {
            "label": "enum GroupMembership.GroupType",
            "members": [
              "ANNOUNCEMENT",
              "SOCIAL"
            ],
            "numberOfBytes": "1"
          },
          "t_mapping(t_uint256,t_array(t_uint256)dyn_storage)": {
            "label": "mapping(uint256 => uint256[])",
            "numberOfBytes": "32"
          },
          "t_mapping(t_uint256,t_mapping(t_uint256,t_uint256))": {
            "label": "mapping(uint256 => mapping(uint256 => uint256))",
            "numberOfBytes": "32"
          },
          "t_mapping(t_uint256,t_struct(DappSettingSnapshot)4849_storage)": {
            "label": "mapping(uint256 => struct GroupMembership.DappSettingSnapshot)",
            "numberOfBytes": "32"
          },
          "t_mapping(t_uint256,t_struct(Group)4871_storage)": {
            "label": "mapping(uint256 => struct GroupMembership.Group)",
            "numberOfBytes": "32"
          },
          "t_mapping(t_uint256,t_uint256)": {
            "label": "mapping(uint256 => uint256)",
            "numberOfBytes": "32"
          },
          "t_struct(DappSettingSnapshot)4849_storage": {
            "label": "struct GroupMembership.DappSettingSnapshot",
            "members": [
              {
                "label": "protocolFeePercent",
                "type": "t_uint256",
                "offset": 0,
                "slot": "0"
              },
              {
                "label": "subjectFeePercent",
                "type": "t_uint256",
                "offset": 0,
                "slot": "1"
              }
            ],
            "numberOfBytes": "64"
          },
          "t_struct(Group)4871_storage": {
            "label": "struct GroupMembership.Group",
            "members": [
              {
                "label": "supply",
                "type": "t_uint32",
                "offset": 0,
                "slot": "0"
              },
              {
                "label": "index",
                "type": "t_uint32",
                "offset": 4,
                "slot": "0"
              },
              {
                "label": "locked",
                "type": "t_bool",
                "offset": 8,
                "slot": "0"
              },
              {
                "label": "groupType",
                "type": "t_enum(GroupType)4839",
                "offset": 9,
                "slot": "0"
              },
              {
                "label": "sumGroupBondValues",
                "type": "t_uint256",
                "offset": 0,
                "slot": "1"
              },
              {
                "label": "sumGroupTimestamp",
                "type": "t_uint256",
                "offset": 0,
                "slot": "2"
              },
              {
                "label": "creator",
                "type": "t_address",
                "offset": 0,
                "slot": "3"
              },
              {
                "label": "minimumJoinAmount",
                "type": "t_uint256",
                "offset": 0,
                "slot": "4"
              },
              {
                "label": "groupFeeAmount",
                "type": "t_uint256",
                "offset": 0,
                "slot": "5"
              },
              {
                "label": "originalBondValueMultiplier",
                "type": "t_uint256",
                "offset": 0,
                "slot": "6"
              }
            ],
            "numberOfBytes": "224"
          },
          "t_uint32": {
            "label": "uint32",
            "numberOfBytes": "4"
          }
        },
        "namespaces": {
          "erc7201:openzeppelin.storage.ERC721": [
            {
              "contract": "ERC721Upgradeable",
              "label": "_name",
              "type": "t_string_storage",
              "src": "@openzeppelin/contracts-upgradeable/token/ERC721/ERC721Upgradeable.sol:27",
              "offset": 0,
              "slot": "0"
            },
            {
              "contract": "ERC721Upgradeable",
              "label": "_symbol",
              "type": "t_string_storage",
              "src": "@openzeppelin/contracts-upgradeable/token/ERC721/ERC721Upgradeable.sol:30",
              "offset": 0,
              "slot": "1"
            },
            {
              "contract": "ERC721Upgradeable",
              "label": "_owners",
              "type": "t_mapping(t_uint256,t_address)",
              "src": "@openzeppelin/contracts-upgradeable/token/ERC721/ERC721Upgradeable.sol:32",
              "offset": 0,
              "slot": "2"
            },
            {
              "contract": "ERC721Upgradeable",
              "label": "_balances",
              "type": "t_mapping(t_address,t_uint256)",
              "src": "@openzeppelin/contracts-upgradeable/token/ERC721/ERC721Upgradeable.sol:34",
              "offset": 0,
              "slot": "3"
            },
            {
              "contract": "ERC721Upgradeable",
              "label": "_tokenApprovals",
              "type": "t_mapping(t_uint256,t_address)",
              "src": "@openzeppelin/contracts-upgradeable/token/ERC721/ERC721Upgradeable.sol:36",
              "offset": 0,
              "slot": "4"
            },
            {
              "contract": "ERC721Upgradeable",
              "label": "_operatorApprovals",
              "type": "t_mapping(t_address,t_mapping(t_address,t_bool))",
              "src": "@openzeppelin/contracts-upgradeable/token/ERC721/ERC721Upgradeable.sol:38",
              "offset": 0,
              "slot": "5"
            }
          ],
          "erc7201:openzeppelin.storage.Initializable": [
            {
              "contract": "Initializable",
              "label": "_initialized",
              "type": "t_uint64",
              "src": "@openzeppelin/contracts-upgradeable/proxy/utils/Initializable.sol:69",
              "offset": 0,
              "slot": "0"
            },
            {
              "contract": "Initializable",
              "label": "_initializing",
              "type": "t_bool",
              "src": "@openzeppelin/contracts-upgradeable/proxy/utils/Initializable.sol:73",
              "offset": 8,
              "slot": "0"
            }
          ]
        }
      }
    },
    "8090b1a40cbb07ab652a3a5ebc8eb52c4b7adb40000a4e6ff6f6506dc80e18fd": {
      "address": "0xe305140857f2B642feEf51feff56EEcF2f4fe39a",
      "txHash": "0x5c9b867facb9fb09fe4e086e653fea99f5e175ee53d905fd3d53194afad291ad",
      "layout": {
        "solcVersion": "0.8.20",
        "storage": [
          {
            "label": "protocolFeePercent",
            "offset": 0,
            "slot": "0",
            "type": "t_uint256",
            "contract": "SuperDapp",
            "src": "contracts/Dev/SuperDapp.sol:20"
          },
          {
            "label": "subjectFeePercent",
            "offset": 0,
            "slot": "1",
            "type": "t_uint256",
            "contract": "SuperDapp",
            "src": "contracts/Dev/SuperDapp.sol:21"
          },
          {
            "label": "groupIndex",
            "offset": 0,
            "slot": "2",
            "type": "t_uint256",
            "contract": "SuperDapp",
            "src": "contracts/Dev/SuperDapp.sol:23"
          },
          {
            "label": "treasuryAddress",
            "offset": 0,
            "slot": "3",
            "type": "t_address",
            "contract": "SuperDapp",
            "src": "contracts/Dev/SuperDapp.sol:25"
          },
          {
            "label": "suprToken",
            "offset": 0,
            "slot": "4",
            "type": "t_contract(IERC20)2627",
            "contract": "SuperDapp",
            "src": "contracts/Dev/SuperDapp.sol:27"
          },
          {
            "label": "mapDeposits",
            "offset": 0,
            "slot": "5",
            "type": "t_mapping(t_address,t_uint256)",
            "contract": "SuperDapp",
            "src": "contracts/Dev/SuperDapp.sol:28"
          },
          {
            "label": "groupMembership",
            "offset": 0,
            "slot": "6",
            "type": "t_contract(GroupMembership)5901",
            "contract": "SuperDapp",
            "src": "contracts/Dev/SuperDapp.sol:29"
          },
          {
            "label": "groupMembershipAddress",
            "offset": 0,
            "slot": "7",
            "type": "t_address",
            "contract": "SuperDapp",
            "src": "contracts/Dev/SuperDapp.sol:30"
          },
          {
            "label": "totalBuyAmount",
            "offset": 0,
            "slot": "8",
            "type": "t_mapping(t_address,t_uint256)",
            "contract": "SuperDapp",
            "src": "contracts/Dev/SuperDapp.sol:31"
          },
          {
            "label": "totalSellAmount",
            "offset": 0,
            "slot": "9",
            "type": "t_mapping(t_address,t_uint256)",
            "contract": "SuperDapp",
            "src": "contracts/Dev/SuperDapp.sol:32"
          },
          {
            "label": "tokenInitialPrices",
            "offset": 0,
            "slot": "10",
            "type": "t_mapping(t_uint256,t_uint256)",
            "contract": "SuperDapp",
            "src": "contracts/Dev/SuperDapp.sol:33"
          }
        ],
        "types": {
          "t_address": {
            "label": "address",
            "numberOfBytes": "20"
          },
          "t_bool": {
            "label": "bool",
            "numberOfBytes": "1"
          },
          "t_struct(InitializableStorage)65_storage": {
            "label": "struct Initializable.InitializableStorage",
            "members": [
              {
                "label": "_initialized",
                "type": "t_uint64",
                "offset": 0,
                "slot": "0"
              },
              {
                "label": "_initializing",
                "type": "t_bool",
                "offset": 8,
                "slot": "0"
              }
            ],
            "numberOfBytes": "32"
          },
          "t_struct(OwnableStorage)14_storage": {
            "label": "struct OwnableUpgradeable.OwnableStorage",
            "members": [
              {
                "label": "_owner",
                "type": "t_address",
                "offset": 0,
                "slot": "0"
              }
            ],
            "numberOfBytes": "32"
          },
          "t_struct(ReentrancyGuardStorage)412_storage": {
            "label": "struct ReentrancyGuardUpgradeable.ReentrancyGuardStorage",
            "members": [
              {
                "label": "_status",
                "type": "t_uint256",
                "offset": 0,
                "slot": "0"
              }
            ],
            "numberOfBytes": "32"
          },
          "t_uint256": {
            "label": "uint256",
            "numberOfBytes": "32"
          },
          "t_uint64": {
            "label": "uint64",
            "numberOfBytes": "8"
          },
          "t_contract(GroupMembership)5901": {
            "label": "contract GroupMembership",
            "numberOfBytes": "20"
          },
          "t_contract(IERC20)2627": {
            "label": "contract IERC20",
            "numberOfBytes": "20"
          },
          "t_mapping(t_address,t_uint256)": {
            "label": "mapping(address => uint256)",
            "numberOfBytes": "32"
          },
          "t_mapping(t_uint256,t_uint256)": {
            "label": "mapping(uint256 => uint256)",
            "numberOfBytes": "32"
          }
        },
        "namespaces": {
          "erc7201:openzeppelin.storage.ReentrancyGuard": [
            {
              "contract": "ReentrancyGuardUpgradeable",
              "label": "_status",
              "type": "t_uint256",
              "src": "@openzeppelin/contracts-upgradeable/utils/ReentrancyGuardUpgradeable.sol:40",
              "offset": 0,
              "slot": "0"
            }
          ],
          "erc7201:openzeppelin.storage.Ownable": [
            {
              "contract": "OwnableUpgradeable",
              "label": "_owner",
              "type": "t_address",
              "src": "@openzeppelin/contracts-upgradeable/access/OwnableUpgradeable.sol:24",
              "offset": 0,
              "slot": "0"
            }
          ],
          "erc7201:openzeppelin.storage.Initializable": [
            {
              "contract": "Initializable",
              "label": "_initialized",
              "type": "t_uint64",
              "src": "@openzeppelin/contracts-upgradeable/proxy/utils/Initializable.sol:69",
              "offset": 0,
              "slot": "0"
            },
            {
              "contract": "Initializable",
              "label": "_initializing",
              "type": "t_bool",
              "src": "@openzeppelin/contracts-upgradeable/proxy/utils/Initializable.sol:73",
              "offset": 8,
              "slot": "0"
            }
          ]
        }
      }
    }
  }
}
